eval_to_go/__init__.py
eval_to_go/evaluation.py
eval_to_go/main.py
eval_to_go/models.py
eval_to_go/prompt_templates.py
tests/__init__.py
tests/test_evaluation.py
eval_to_go-0.1.1.dist-info/LICENSE
eval_to_go-0.1.1.dist-info/METADATA
eval_to_go-0.1.1.dist-info/WHEEL
eval_to_go-0.1.1.dist-info/top_level.txt
eval_to_go-0.1.1.dist-info/RECORD
