Metadata-Version: 2.1
Name: eval-to-go
Version: 0.1.1
Summary: Your go-to, no-fuss eval for zapping through RAG and LLM evaluations! For a busy person who's too swamped to wrestle with the behemoths of professional setups
Home-page: UNKNOWN
Author: Asghar Ghorbani
Author-email: ghorbani59@gmail.com
License: UNKNOWN
Platform: UNKNOWN
Classifier: Programming Language :: Python :: 3
Classifier: License :: OSI Approved :: MIT License
Classifier: Operating System :: OS Independent
Requires-Python: >=3.9
License-File: LICENSE
Requires-Dist: pandas >=2.0.0
Requires-Dist: openai >=0.10.0
Requires-Dist: h2ogpte >=1.3.0
Requires-Dist: python-dotenv >=1.0.0
